libheader/__init__.py
libheader/__main__.py
libheader/_version.py
libheader/gcclh.py
libheader/lh.py
libheader/makelh.py
libheader-1.1.0.data/scripts/gcclh
libheader-1.1.0.data/scripts/gcclh.py
libheader-1.1.0.data/scripts/makelh
libheader-1.1.0.data/scripts/makelh.py
libheader-1.1.0.dist-info/METADATA
libheader-1.1.0.dist-info/WHEEL
libheader-1.1.0.dist-info/top_level.txt
libheader-1.1.0.dist-info/RECORD
