Metadata-Version: 2.1
Name: libheader
Version: 1.1.0
Summary: A new file format that makes C easier.
Home-page: https://github.com/wk1093/libheader
Author: Wyatt Kloos
Author-email: wyattk1093@gmail.com
License: BSD 2-clause
Classifier: License :: OSI Approved :: BSD License
Classifier: Programming Language :: Python :: 3
Classifier: Programming Language :: Python :: 3.4
Classifier: Programming Language :: Python :: 3.5
